feeling/__init__.py
feeling/__main__.py
feeling/chui.py
feeling/cli.py
feeling/data/__init__.py
feeling/data/feelings.py
feeling/data/storage.py
feeling/screens/__init__.py
feeling/screens/main.py
feeling_cli-0.0.1.dist-info/METADATA
feeling_cli-0.0.1.dist-info/WHEEL
feeling_cli-0.0.1.dist-info/entry_points.txt
feeling_cli-0.0.1.dist-info/top_level.txt
feeling_cli-0.0.1.dist-info/RECORD
