Metadata-Version: 2.1
Name: feeling-cli
Version: 0.0.1
Summary: A simple feelings recorder and viewer for the terminal, built with Textual
Home-page: https://github.com/davep/feeling
Author: Dave Pearson
Author-email: davep@davep.org
Maintainer: Dave Pearson
Maintainer-email: davep@davep.org
License: License :: OSI Approved :: GNU General Public License v3 or later (GPLv3+)
Project-URL: Documentation, https://github.com/davep/feeling/blob/main/README.md
Project-URL: Source, https://github.com/davep/feeling
Project-URL: Issues, https://github.com/davep/feeling/issues
Project-URL: Discussions, https://github.com/davep/feeling/discussions
Keywords: terminal,library,feelings
Classifier: License :: OSI Approved :: MIT License
Classifier: Environment :: Console
Classifier: Development Status :: 3 - Alpha
Classifier: Intended Audience :: End Users/Desktop
Classifier: Operating System :: OS Independent
Classifier: Programming Language :: Python :: 3.10
Classifier: Programming Language :: Python :: 3.11
Requires-Python: >=3.10
Requires-Dist: textual (==0.15.1)
Requires-Dist: xdg
